Metadata-Version: 2.1
Name: youtube-playlist-videos-scraper-python
Version: 1.0.0
Summary: A python library to scrape playlist videos data from youtube automatically.
Home-page: https://youtube-api.datakund.com/en/latest/
Author: DataKund
Author-email: datakund@gmail.com
License: Apache License 2.0
Keywords: youtube python bot_studio playlist videos scraper data web-scraping
Platform: UNKNOWN
